AUTHORS.rst
CONTRIBUTING.rst
HISTORY.rst
LICENSE
MANIFEST.in
README.md
setup.py
django_suit_sortable.egg-info/PKG-INFO
django_suit_sortable.egg-info/SOURCES.txt
django_suit_sortable.egg-info/dependency_links.txt
django_suit_sortable.egg-info/not-zip-safe
django_suit_sortable.egg-info/top_level.txt
suit_sortable/__init__.py
suit_sortable/admin.py
suit_sortable/models.py
suit_sortable/static/js/jquery-ui-1.10.3.sortable.min.js
suit_sortable/static/js/sortable.changelist.js
suit_sortable/static/js/sortable.stacked.inline.js
suit_sortable/static/js/sortable.tabular.inline.js