Metadata-Version: 1.1
Name: django-suit-sortable
Version: 0.1.0
Summary: Drag-and-drop ordering for objects and inlines in Django admin using django-suit.
Home-page: https://github.com/JP74/django-suit-sortable
Author: Mishbah Razzaque
Author-email: mishbah@jp74.com
License: BSD
Keywords: suit_sortable
Platform: UNKNOWN
Classifier: Development Status :: 2 - Pre-Alpha
Classifier: Framework :: Django
Classifier: Intended Audience :: Developers
Classifier: License :: OSI Approved :: BSD License
Classifier: Natural Language :: English
Classifier: Programming Language :: Python :: 2
Classifier: Programming Language :: Python :: 2.6
Classifier: Programming Language :: Python :: 2.7
Classifier: Programming Language :: Python :: 3
Classifier: Programming Language :: Python :: 3.3
